cli.py
index.py
meshcoredecoder/__init__.py
meshcoredecoder/crypto/__init__.py
meshcoredecoder/crypto/channel_crypto.py
meshcoredecoder/crypto/ed25519_verifier.py
meshcoredecoder/crypto/key_manager.py
meshcoredecoder/decoder/__init__.py
meshcoredecoder/decoder/packet_decoder.py
meshcoredecoder/decoder/payload_decoders/__init__.py
meshcoredecoder/decoder/payload_decoders/ack.py
meshcoredecoder/decoder/payload_decoders/advert.py
meshcoredecoder/decoder/payload_decoders/anon_request.py
meshcoredecoder/decoder/payload_decoders/group_text.py
meshcoredecoder/decoder/payload_decoders/path.py
meshcoredecoder/decoder/payload_decoders/request.py
meshcoredecoder/decoder/payload_decoders/response.py
meshcoredecoder/decoder/payload_decoders/text_message.py
meshcoredecoder/decoder/payload_decoders/trace.py
meshcoredecoder/types/__init__.py
meshcoredecoder/types/crypto.py
meshcoredecoder/types/enums.py
meshcoredecoder/types/packet.py
meshcoredecoder/types/payloads.py
meshcoredecoder/utils/__init__.py
meshcoredecoder/utils/auth_token.py
meshcoredecoder/utils/enum_names.py
meshcoredecoder/utils/hex.py
meshcoredecoder-0.1.3.dist-info/licenses/LICENSE
meshcoredecoder-0.1.3.dist-info/METADATA
meshcoredecoder-0.1.3.dist-info/WHEEL
meshcoredecoder-0.1.3.dist-info/entry_points.txt
meshcoredecoder-0.1.3.dist-info/top_level.txt
meshcoredecoder-0.1.3.dist-info/RECORD
