Metadata-Version: 2.4
Name: meshcoredecoder
Version: 0.1.3
Summary: Complete Python implementation of the MeshCore Packet Decoder
Home-page: https://github.com/chrisdavis2110/meshcore-decoder-py
Author: Chris Davis
Author-email: Chris Davis <chrisdavis2110@gmail.com>, Michael Hart <michaelhart@michaelhart.me>
License: MIT
Project-URL: Homepage, https://github.com/chrisdavis2110/meshcore-decoder-py
Project-URL: Repository, https://github.com/chrisdavis2110/meshcore-decoder-py
Project-URL: Issues, https://github.com/chrisdavis2110/meshcore-decoder-py/issues
Keywords: meshcore,decoder,packet,mesh,networking
Classifier: Development Status :: 4 - Beta
Classifier: Intended Audience :: Developers
Classifier: License :: OSI Approved :: MIT License
Classifier: Operating System :: OS Independent
Classifier: Programming Language :: Python :: 3
Classifier: Programming Language :: Python :: 3.8
Classifier: Programming Language :: Python :: 3.9
Classifier: Programming Language :: Python :: 3.10
Classifier: Programming Language :: Python :: 3.11
Classifier: Programming Language :: Python :: 3.12
Classifier: Programming Language :: Python :: 3.13
Requires-Python: >=3.8
License-File: LICENSE
Requires-Dist: pycryptodome>=3.19.0
Requires-Dist: cryptography>=41.0.0
Requires-Dist: click>=8.1.0
Provides-Extra: dev
Requires-Dist: pytest>=7.0.0; extra == "dev"
Requires-Dist: pytest-cov>=4.0.0; extra == "dev"
Requires-Dist: black>=23.0.0; extra == "dev"
Requires-Dist: pylint>=2.17.0; extra == "dev"
Dynamic: author
Dynamic: home-page
Dynamic: license-file
Dynamic: requires-python
